realutils/__init__.py
realutils/config/__init__.py
realutils/config/meta.py
realutils/detect/__init__.py
realutils/detect/face.py
realutils/detect/head.py
realutils/detect/person.py
realutils/detect/real_face.py
realutils/detect/yolo.py
realutils/face/__init__.py
realutils/face/insightface/__init__.py
realutils/face/insightface/analysis.py
realutils/face/insightface/base.py
realutils/face/insightface/detect.py
realutils/face/insightface/extract.py
realutils/face/insightface/genderage.py
realutils/face/insightface/visual.py
realutils/metrics/__init__.py
realutils/metrics/clip.py
realutils/metrics/dinov2.py
realutils/metrics/siglip.py
realutils/tagging/__init__.py
realutils/tagging/idolsankaku.py
dghs_realutils-0.1.1.dist-info/LICENSE
dghs_realutils-0.1.1.dist-info/METADATA
dghs_realutils-0.1.1.dist-info/WHEEL
dghs_realutils-0.1.1.dist-info/top_level.txt
dghs_realutils-0.1.1.dist-info/RECORD
