Metadata-Version: 2.1
Name: dghs-realutils
Version: 0.1.1
Summary: A convenient and user-friendly image data processing library that integrates various advanced image processing models.
Home-page: https://github.com/deepghs/realutils
Author: narugo1992
Author-email: narugo1992@deepghs.org
License: GNU Lesser General Public License v3 or later (LGPLv3+)
Keywords: image-processing,computer-vision,deep-learning,data-augmentation
Classifier: Development Status :: 5 - Production/Stable
Classifier: Intended Audience :: Developers
Classifier: Intended Audience :: Science/Research
Classifier: Intended Audience :: Information Technology
Classifier: License :: OSI Approved :: GNU Lesser General Public License v3 or later (LGPLv3+)
Classifier: Programming Language :: Python
Classifier: Programming Language :: Python :: 3
Classifier: Programming Language :: Python :: 3 :: Only
Classifier: Programming Language :: Python :: 3.8
Classifier: Programming Language :: Python :: 3.9
Classifier: Programming Language :: Python :: 3.10
Classifier: Programming Language :: Python :: 3.11
Classifier: Programming Language :: Python :: 3.12
Classifier: Operating System :: OS Independent
Classifier: Operating System :: POSIX
Classifier: Operating System :: Microsoft :: Windows
Classifier: Operating System :: MacOS
Classifier: Topic :: Scientific/Engineering
Classifier: Topic :: Scientific/Engineering :: Image Processing
Classifier: Topic :: Multimedia :: Graphics
Classifier: Topic :: Software Development :: Libraries
Classifier: Topic :: Software Development :: Libraries :: Python Modules
Classifier: Typing :: Typed
Classifier: Natural Language :: English
Requires-Python: >=3.8
License-File: LICENSE
Requires-Dist: hbutils >=0.9.0
Requires-Dist: pillow
Requires-Dist: numpy <2
Requires-Dist: scikit-learn
Requires-Dist: huggingface-hub
Requires-Dist: tqdm
Requires-Dist: opencv-python
Requires-Dist: opencv-contrib-python
Requires-Dist: pandas
Requires-Dist: scipy
Requires-Dist: emoji <2.12,>=2.5.0
Requires-Dist: pilmoji >=1.3.0
Requires-Dist: deprecation >=2.0.0
Requires-Dist: hfutils >=0.4.2
Requires-Dist: filelock
Requires-Dist: dghs-imgutils >=0.11.0
Requires-Dist: shapely !=2.0.7
Requires-Dist: scikit-image >=0.21
Requires-Dist: tokenizers <0.21,>=0.20.0 ; python_version < "3.9"
Requires-Dist: tokenizers >=0.20.0 ; python_version >= "3.9"
Provides-Extra: doc
Requires-Dist: Jinja2 ~=3.0.0 ; extra == 'doc'
Requires-Dist: sphinx >=3.2.0 ; extra == 'doc'
Requires-Dist: sphinx-rtd-theme >=0.4.3 ; extra == 'doc'
Requires-Dist: enum-tools ~=0.9.0 ; extra == 'doc'
Requires-Dist: sphinx-toolbox ; extra == 'doc'
Requires-Dist: plantumlcli >=0.0.2 ; extra == 'doc'
Requires-Dist: packaging ; extra == 'doc'
Requires-Dist: sphinx-multiversion >=0.2.4 ; extra == 'doc'
Requires-Dist: where ~=1.0.2 ; extra == 'doc'
Requires-Dist: easydict <2,>=1.7 ; extra == 'doc'
Requires-Dist: responses >=0.20.0 ; extra == 'doc'
Requires-Dist: matplotlib ; extra == 'doc'
Requires-Dist: natsort ; extra == 'doc'
Requires-Dist: nbsphinx >=0.8.8 ; extra == 'doc'
Requires-Dist: ipython >=7.16.3 ; extra == 'doc'
Requires-Dist: psutil >=5.8.0 ; extra == 'doc'
Requires-Dist: ipykernel >=6.15 ; extra == 'doc'
Requires-Dist: py-cpuinfo >=8.0.0 ; extra == 'doc'
Requires-Dist: click >=7.0.0 ; extra == 'doc'
Provides-Extra: gpu
Requires-Dist: dghs-imgutils[gpu] ; extra == 'gpu'
Provides-Extra: test
Requires-Dist: coverage >=5 ; extra == 'test'
Requires-Dist: mock >=4.0.3 ; extra == 'test'
Requires-Dist: flake8 ~=3.5 ; extra == 'test'
Requires-Dist: testfixtures >=6.18.5 ; extra == 'test'
Requires-Dist: pytest ~=6.2.5 ; extra == 'test'
Requires-Dist: pytest-cov ~=3.0.0 ; extra == 'test'
Requires-Dist: pytest-mock ~=3.6.1 ; extra == 'test'
Requires-Dist: pytest-xdist >=1.34.0 ; extra == 'test'
Requires-Dist: pytest-rerunfailures ~=10.2 ; extra == 'test'
Requires-Dist: pytest-timeout ~=2.0.2 ; extra == 'test'
Requires-Dist: pytest-benchmark ~=3.4.0 ; extra == 'test'
Requires-Dist: easydict <2,>=1.7 ; extra == 'test'
Requires-Dist: testtools >=2 ; extra == 'test'
Requires-Dist: where >=1.0.2 ; extra == 'test'
Requires-Dist: pytest-image-diff >=0.0.11 ; extra == 'test'
Requires-Dist: matplotlib ; extra == 'test'
Requires-Dist: natsort ; extra == 'test'
